textuals_custom_components/__init__.py
textuals_custom_components/timefunctions.py
textuals_custom_components-0.0.4.dist-info/METADATA
textuals_custom_components-0.0.4.dist-info/WHEEL
textuals_custom_components-0.0.4.dist-info/top_level.txt
textuals_custom_components-0.0.4.dist-info/RECORD
