Metadata-Version: 2.1
Name: textuals-custom-components
Version: 0.0.4
Summary: Read the latest Real Python tutorials
Author: ThoStart
Author-email: Thomas <1234@gmail.com>
Project-URL: Homepage, https://github.com/pypa/sampleproject
Project-URL: Bug Tracker, https://github.com/pypa/sampleproject/issues
Classifier: License :: OSI Approved :: MIT License
Classifier: Programming Language :: Python
Classifier: Programming Language :: Python :: 3
Requires-Python: >=3.9
